src/__init__.py
src/main.py
num2name-0.0.1.dist-info/LICENSE
num2name-0.0.1.dist-info/METADATA
num2name-0.0.1.dist-info/WHEEL
num2name-0.0.1.dist-info/top_level.txt
num2name-0.0.1.dist-info/RECORD
